batchwise/__init__.py
batchwise/__main__.py
batchwise/_version.py
batchwise/cli.py
batchwise/config.py
batchwise/constants.py
batchwise/dataset.py
batchwise/engine.py
batchwise/processor.py
batchwise/store.py
batchwise-0.1.0.dist-info/METADATA
batchwise-0.1.0.dist-info/WHEEL
batchwise-0.1.0.dist-info/entry_points.txt
batchwise-0.1.0.dist-info/licenses/LICENSE
batchwise-0.1.0.dist-info/RECORD
